README.md
setup.py
twitter_profile_scraper_python/__init__.py
twitter_profile_scraper_python.egg-info/PKG-INFO
twitter_profile_scraper_python.egg-info/SOURCES.txt
twitter_profile_scraper_python.egg-info/dependency_links.txt
twitter_profile_scraper_python.egg-info/requires.txt
twitter_profile_scraper_python.egg-info/top_level.txt